drf_query_filter/fields.py
drf_query_filter/filters.py
drf_query_filter/mixins.py
drf_query_filter/utils.py
drf_query_filter-0.1.8.5.dist-info/LICENSE
drf_query_filter-0.1.8.5.dist-info/METADATA
drf_query_filter-0.1.8.5.dist-info/WHEEL
drf_query_filter-0.1.8.5.dist-info/top_level.txt
drf_query_filter-0.1.8.5.dist-info/RECORD
