Metadata-Version: 2.1
Name: drf-query-filter
Version: 0.1.8.5
Summary: A django app to apply filters on drf queryset using the query params with custom fields.
Home-page: https://github.com/Jmillan-Dev/drf-query-filter
Author: Josué Millán Zamora
Author-email: hi@jmillan.me
License: MIT License
Keywords: drf-query-filter filters queryparameters django restframework
Platform: UNKNOWN
Classifier: Development Status :: 3 - Alpha
Classifier: Intended Audience :: Developers
Classifier: Framework :: Django
Classifier: License :: OSI Approved :: MIT License
Classifier: Programming Language :: Python
Classifier: Programming Language :: Python :: 3
Classifier: Programming Language :: Python :: 3.2
Classifier: Programming Language :: Python :: 3.3
Classifier: Programming Language :: Python :: 3.4
Classifier: Programming Language :: Python :: 3.7
Classifier: Programming Language :: Python :: 3.10
Classifier: Topic :: Internet :: WWW/HTTP
License-File: LICENSE
Requires-Dist: Django (>=1.8.11)
Requires-Dist: djangorestframework (>=3.3.3)
